{
  "categories": [
    {
      "id": 1,
      "content": "Satélites",
      "details": "Exploración de satélites espaciales",

      "products": [

        {
          "id": 1,
          "content": "Starlink",
          "picture": "starlink",
          "type": "Comunicaciones",
          "agency": "SpaceX",
          "country": "Estados Unidos",
          "year": 2019,
          "orbit": "Órbita baja terrestre (LEO)",
          "status": "Activo",
          "details": "Starlink es una constelación de satélites desarrollada por SpaceX para proporcionar Internet de alta velocidad en cualquier parte del mundo.",
          "curiosity": "Actualmente existen miles de satélites Starlink en órbita."
        },

        {
          "id": 2,
          "content": "METEOSAT-11",
          "picture": "meteosat11",
          "type": "Meteorológico",
          "agency": "EUMETSAT",
          "country": "Europa",
          "year": 2015,
          "orbit": "Órbita geoestacionaria (GEO)",
          "status": "Activo",
          "details": "METEOSAT-11 es un satélite meteorológico europeo utilizado para la observación climática y predicción del tiempo.",
          "curiosity": "Ayuda a detectar tormentas y fenómenos atmosféricos en tiempo real."
        },

        {
          "id": 3,
          "content": "Hispasat 30W-6",
          "picture": "hispasat",
          "type": "Comunicaciones",
          "agency": "Hispasat",
          "country": "España",
          "year": 2018,
          "orbit": "Órbita geoestacionaria (GEO)",
          "status": "Activo",
          "details": "Hispasat 30W-6 es un satélite de comunicaciones operado por la empresa española Hispasat.",
          "curiosity": "Forma parte de una de las principales redes de comunicaciones de España."
        },

        {
          "id": 4,
          "content": "Galileo GSAT0201",
          "picture": "galileo",
          "type": "Navegación",
          "agency": "ESA",
          "country": "Europa",
          "year": 2011,
          "orbit": "Órbita media terrestre (MEO)",
          "status": "Activo",
          "details": "Galileo GSAT0201 pertenece al sistema europeo de navegación Galileo.",
          "curiosity": "Galileo es el equivalente europeo del GPS estadounidense."
        },

        {
          "id": 5,
          "content": "GPS IIF-10",
          "picture": "gps",
          "type": "Navegación",
          "agency": "US Space Force",
          "country": "Estados Unidos",
          "year": 2015,
          "orbit": "Órbita media terrestre (MEO)",
          "status": "Activo",
          "details": "GPS IIF-10 forma parte de la red de satélites GPS utilizada para navegación global.",
          "curiosity": "Los satélites GPS permiten la localización precisa en teléfonos móviles y vehículos."
        }

      ]
    },

    {
      "id": 2,
      "content": "Misiones",
      "details": "Misiones espaciales históricas e importantes",

      "products": [

        {
          "id": 6,
          "content": "Apollo 11",
          "picture": "apollo11",
          "type": "Misión lunar",
          "agency": "NASA",
          "country": "Estados Unidos",
          "year": 1969,
          "orbit": "Objetivo: primer alunizaje tripulado",
          "status": "Completada",
          "details": "Apollo 11 fue la primera misión espacial tripulada que logró llevar humanos a la Luna.",
          "curiosity": "Neil Armstrong pronunció la famosa frase: un pequeño paso para el hombre, un gran salto para la humanidad."
        },

        {
          "id": 7,
          "content": "Artemis I",
          "picture": "artemis1",
          "type": "Exploración lunar",
          "agency": "NASA",
          "country": "Estados Unidos",
          "year": 2022,
          "orbit": "Objetivo: regreso a la Luna",
          "status": "Completada",
          "details": "Artemis I fue la primera misión del programa Artemis para preparar futuras misiones tripuladas a la Luna.",
          "curiosity": "La nave Orion viajó miles de kilómetros más allá de la Luna."
        },

        {
          "id": 8,
          "content": "Mars Pathfinder",
          "picture": "pathfinder",
          "type": "Exploración planetaria",
          "agency": "NASA",
          "country": "Estados Unidos",
          "year": 1996,
          "orbit": "Objetivo: exploración de Marte",
          "status": "Completada",
          "details": "Mars Pathfinder fue una misión robótica enviada a Marte para estudiar su superficie y atmósfera.",
          "curiosity": "Incluyó el rover Sojourner, uno de los primeros vehículos en Marte."
        },

        {
          "id": 9,
          "content": "Hubble Space Telescope",
          "picture": "hubble",
          "type": "Observación espacial",
          "agency": "NASA / ESA",
          "country": "Estados Unidos",
          "year": 1990,
          "orbit": "Órbita baja terrestre (LEO)",
          "status": "Activo",
          "details": "El telescopio espacial Hubble ha permitido obtener algunas de las imágenes más importantes del universo.",
          "curiosity": "Ha observado galaxias situadas a miles de millones de años luz."
        },

        {
          "id": 10,
          "content": "Voyager 1",
          "picture": "voyager1",
          "type": "Exploración espacial",
          "agency": "NASA",
          "country": "Estados Unidos",
          "year": 1977,
          "orbit": "Objetivo: explorar el Sistema Solar exterior",
          "status": "Activa",
          "details": "Voyager 1 es una sonda espacial enviada para estudiar Júpiter y Saturno.",
          "curiosity": "Es el objeto humano más alejado de la Tierra."
        }

      ]
    }
  ]
}